hocr_utils/__init__.py
hocr_utils/utils.py
tests/__init__.py
tests/test_utils.py
hocr_utils-0.0.3.dist-info/LICENSE
hocr_utils-0.0.3.dist-info/METADATA
hocr_utils-0.0.3.dist-info/WHEEL
hocr_utils-0.0.3.dist-info/top_level.txt
hocr_utils-0.0.3.dist-info/RECORD
