Metadata-Version: 2.1
Name: hocr-utils
Version: 0.0.3
Summary: Package containing utility function for hOCR and tesseract
Home-page: https://github.com/Mrmarx/hocr_utils
Author: Antoine Dubuis
Author-email: antoine.dubuis@gmail.com
Project-URL: Homepage, https://github.com/Mrmarx/hocr-utils
Keywords: hocr tesseract utility
Classifier: Programming Language :: Python :: 3.7
Classifier: Programming Language :: Python :: 3.8
Classifier: Programming Language :: Python :: 3.9
Classifier: Topic :: Utilities
Classifier: License :: OSI Approved :: MIT License
Requires-Python: >=3.7
License-File: LICENSE
Requires-Dist: matplotlib (>=3.3.0)
Requires-Dist: pytesseract (>=0.3.7)
Requires-Dist: numpy (>=1.20.2)
Requires-Dist: pdf2image (>=1.14.0)
Requires-Dist: beautifulsoup4 (>=4.9.3)
Requires-Dist: lxml (>=4.6.3)
Requires-Dist: pip (>=9)
Requires-Dist: setuptools (>=26)
Requires-Dist: twine
Requires-Dist: wheel (>=0.29)
